yann_utils/__init__.py
yann_utils/chunking.py
yann_utils/utils.py
yann_utils-0.1.1.dist-info/LICENSE
yann_utils-0.1.1.dist-info/METADATA
yann_utils-0.1.1.dist-info/WHEEL
yann_utils-0.1.1.dist-info/RECORD
