Metadata-Version: 2.1
Name: yann-utils
Version: 0.1.1
Summary: 
Author: Yann Hoffmann
Author-email: yann.hoffmaaann@gmail.com
Requires-Python: >=3.9,<4.0
Classifier: Programming Language :: Python :: 3
Classifier: Programming Language :: Python :: 3.9
Classifier: Programming Language :: Python :: 3.10
Classifier: Programming Language :: Python :: 3.11
Requires-Dist: numpy (>=1.25.2,<2.0.0)
